fastrtc_walkie_talkie/__about__.py
fastrtc_walkie_talkie/__init__.py
fastrtc_walkie_talkie-0.0.3.post1.dist-info/METADATA
fastrtc_walkie_talkie-0.0.3.post1.dist-info/WHEEL
fastrtc_walkie_talkie-0.0.3.post1.dist-info/licenses/LICENSE.txt
fastrtc_walkie_talkie-0.0.3.post1.dist-info/RECORD
